matrix_commander/__init__.py
matrix_commander/matrix-commander-tui
matrix_commander/matrix_commander.py
matrix_commander-8.0.5.dist-info/licenses/LICENSE
matrix_commander-8.0.5.dist-info/METADATA
matrix_commander-8.0.5.dist-info/WHEEL
matrix_commander-8.0.5.dist-info/entry_points.txt
matrix_commander-8.0.5.dist-info/top_level.txt
matrix_commander-8.0.5.dist-info/RECORD
