Metadata-Version: 2.4
Name: matrix-commander
Version: 8.0.5
Summary: A simple command-line Matrix client
Home-page: https://github.com/8go/matrix-commander
Author: 8go
Project-URL: Bug Tracker, https://github.com/8go/matrix-commander/issues
Project-URL: repository, https://github.com/8go/matrix-commander
Keywords: Matrix,chat,messaging
Classifier: Programming Language :: Python :: 3.11
Classifier: Programming Language :: Python :: 3.12
Classifier: License :: OSI Approved :: GNU Lesser General Public License v3 or later (LGPLv3+)
Classifier: Operating System :: OS Independent
Classifier: Development Status :: 5 - Production/Stable
Classifier: Intended Audience :: Developers
Classifier: Natural Language :: English
Classifier: Topic :: Communications :: Chat
Requires-Python: >=3.11
License-File: LICENSE
Requires-Dist: aiohttp
Requires-Dist: aiofiles>=0.6.0
Requires-Dist: argparse
Requires-Dist: asyncio
Requires-Dist: async-timeout
Requires-Dist: datetime
Requires-Dist: emoji
Requires-Dist: markdown
Requires-Dist: matrix-nio[e2e]>=0.14.1
Requires-Dist: notify2
Requires-Dist: Pillow
Requires-Dist: python_magic
Requires-Dist: pyxdg
Requires-Dist: uuid
Dynamic: license-file
